walk_up/__init__.py
walk_up/main.py
walk_up-0.1.0.dist-info/METADATA
walk_up-0.1.0.dist-info/WHEEL
walk_up-0.1.0.dist-info/top_level.txt
walk_up-0.1.0.dist-info/RECORD
