Metadata-Version: 2.1
Name: walk-up
Version: 0.1.0
Summary: Find files in parent directories
Home-page: https://github.com/jeff-hykin/walk_up
Author: Jeff Hykin
Author-email: jeff.hykin@gmail.com
License: MIT
Platform: UNKNOWN
Requires-Python: >=3.6
